setup.py
urlsafecrypt/__init__.py
urlsafecrypt/urlsafecrypt.py
urlsafecrypt.egg-info/PKG-INFO
urlsafecrypt.egg-info/SOURCES.txt
urlsafecrypt.egg-info/dependency_links.txt
urlsafecrypt.egg-info/requires.txt
urlsafecrypt.egg-info/top_level.txt