Metadata-Version: 1.0
Name: urlsafecrypt
Version: 0.2
Summary: Provides Fernet based symmetric encryption of data whose output is safe to be used in URLs.
Home-page: https://bitbucket.org/fabian/urlsafecrypt
Author: Fabian Topfstedt
Author-email: topfstedt@schneevonmorgen.com
License: UNKNOWN
Keywords: urlsafe,cryptography
Platform: UNKNOWN
